xaddpy/__init__.py
xaddpy/milp/__init__.py
xaddpy/milp/build.py
xaddpy/milp/solve.py
xaddpy/milp/util.py
xaddpy/utils/__init__.py
xaddpy/utils/global_vars.py
xaddpy/utils/graph.py
xaddpy/utils/logger.py
xaddpy/utils/lp_util.py
xaddpy/utils/symengine.py
xaddpy/utils/util.py
xaddpy/xadd/__init__.py
xaddpy/xadd/node.py
xaddpy/xadd/reduce_lp.py
xaddpy/xadd/xadd.py
xaddpy/xadd/xadd_parse_utils.py
xaddpy-0.2.8.dist-info/LICENSE
xaddpy-0.2.8.dist-info/METADATA
xaddpy-0.2.8.dist-info/WHEEL
xaddpy-0.2.8.dist-info/top_level.txt
xaddpy-0.2.8.dist-info/RECORD
