Metadata-Version: 2.1
Name: xaddpy
Version: 0.2.8
Summary: XADD package in Python
Home-page: https://github.com/jihwan-jeong/xaddpy
Download-URL: https://github.com/jihwan-jeong/xaddpy/archive/refs/tags/0.2.8.tar.gz
Author: Jihwan Jeong
Author-email: Jihwan Jeong <jiihwan.jeong@gmail.com>
License: MIT License
Project-URL: Homepage, https://github.com/jihwan-jeong/xaddpy
Project-URL: Bug Tracker, https://github.com/jihwan-jeong/xaddpy/issues
Keywords: xadd,xadd python,symbolic diagram
Classifier: Programming Language :: Python :: 3
Classifier: License :: OSI Approved :: MIT License
Classifier: Operating System :: OS Independent
Requires-Python: >=3.8
License-File: LICENSE
Requires-Dist: symengine
Requires-Dist: numpy
Requires-Dist: pulp
Requires-Dist: psutil
Requires-Dist: sympy
Requires-Dist: scipy
Requires-Dist: matplotlib
